bubot_helpers/Action.py
bubot_helpers/ActionDecorator.py
bubot_helpers/ArrayHelper.py
bubot_helpers/ExtException.py
bubot_helpers/Helper.py
bubot_helpers/JsonSchema4.py
bubot_helpers/JsonSchemaLoader.py
bubot_helpers/__init__.py
bubot_helpers/preemption.py
bubot_helpers-4.0.4.dist-info/licenses/LICENSE
bubot_helpers-4.0.4.dist-info/METADATA
bubot_helpers-4.0.4.dist-info/WHEEL
bubot_helpers-4.0.4.dist-info/top_level.txt
bubot_helpers-4.0.4.dist-info/RECORD
