Metadata-Version: 2.4
Name: bubot_helpers
Version: 4.0.4
Summary: iot framework based on OCF specification
Home-page: https://github.com/businka/Bubot_Helpers
Author: Razgovorov Mikhail
Author-email: 1338833@gmail.com
Classifier: Programming Language :: Python :: 3
Classifier: License :: OSI Approved :: MIT License
Classifier: Operating System :: OS Independent
Classifier: Development Status :: 3 - Alpha
Classifier: Framework :: AsyncIO
Classifier: License :: OSI Approved :: MIT License
Requires-Python: >=3.7
License-File: LICENSE
Dynamic: author
Dynamic: author-email
Dynamic: classifier
Dynamic: description
Dynamic: description-content-type
Dynamic: home-page
Dynamic: license-file
Dynamic: requires-python
Dynamic: summary
